adbpyg_adapter/__init__.py
adbpyg_adapter/abc.py
adbpyg_adapter/adapter.py
adbpyg_adapter/controller.py
adbpyg_adapter/encoders.py
adbpyg_adapter/exceptions.py
adbpyg_adapter/typings.py
adbpyg_adapter/utils.py
adbpyg_adapter-1.1.3.dist-info/LICENSE
adbpyg_adapter-1.1.3.dist-info/METADATA
adbpyg_adapter-1.1.3.dist-info/WHEEL
adbpyg_adapter-1.1.3.dist-info/top_level.txt
adbpyg_adapter-1.1.3.dist-info/RECORD
