Metadata-Version: 2.1
Name: adbpyg_adapter
Version: 1.1.3
Summary: Convert ArangoDB graphs to PyG & vice-versa.
Author-email: Anthony Mahanna <anthony.mahanna@arangodb.com>
License: Apache License
Project-URL: Homepage, https://github.com/arangoml/pyg-adapter
Keywords: arangodb,pyg,pytorch,pytorch geometric,adapter
Classifier: Intended Audience :: Developers
Classifier: License :: OSI Approved :: Apache Software License
Classifier: Operating System :: OS Independent
Classifier: Programming Language :: Python :: 3
Classifier: Programming Language :: Python :: 3.8
Classifier: Programming Language :: Python :: 3.9
Classifier: Programming Language :: Python :: 3.10
Classifier: Programming Language :: Python :: 3.11
Classifier: Topic :: Utilities
Classifier: Typing :: Typed
Requires-Python: >=3.8
License-File: LICENSE
Requires-Dist: requests >=2.27.1
Requires-Dist: rich >=12.5.1
Requires-Dist: pandas >=1.3.5
Requires-Dist: python-arango ~=7.6
Requires-Dist: torch >=1.12.0
Requires-Dist: torch-sparse >=0.6.14
Requires-Dist: torch-scatter >=2.0.9
Requires-Dist: torch-geometric >=2.0.4
Requires-Dist: setuptools >=45
Provides-Extra: dev
Requires-Dist: black ==23.3.0 ; extra == 'dev'
Requires-Dist: flake8 ==6.0.0 ; extra == 'dev'
Requires-Dist: Flake8-pyproject ; extra == 'dev'
Requires-Dist: isort ==5.12.0 ; extra == 'dev'
Requires-Dist: mypy ==1.4.1 ; extra == 'dev'
Requires-Dist: pytest >=6.0.0 ; extra == 'dev'
Requires-Dist: pytest-cov >=2.0.0 ; extra == 'dev'
Requires-Dist: coveralls >=3.3.1 ; extra == 'dev'
Requires-Dist: types-setuptools >=57.4.9 ; extra == 'dev'
Requires-Dist: types-requests >=2.27.11 ; extra == 'dev'
Requires-Dist: networkx >=2.5.1 ; extra == 'dev'
